{"cameraMode":{"drawMode":0,"name":"Shaded","section":"Shading Mode"},"sceneLighting":true,"audioPlay":false,"sceneViewState":{"showFog":true,"showMaterialUpdate":false,"showSkybox":true,"showFlares":true,"showImageEffects":true,"showParticleSystems":true},"in2DMode":false,"pivot":{"x":-1.4681713581085206,"y":1.02386474609375,"z":-0.7129602432250977},"rotation":{"x":-0.41077449917793276,"y":-0.004925635643303394,"z":0.002219384303316474,"w":-0.9117214679718018},"size":5.733546257019043,"orthographic":false}